{
  "credit": "Made with Blockbench",
  "texture_size": [32, 32],
  "textures": {
    "0": "bettas:blocks/big_log",
    "particle": "bettas:blocks/big_log"
  },
  "elements": [
    {
      "from": [5.745, -4.22, 8.38],
      "to": [13.515, -4.035, 10.23],
      "rotation": {"angle": -45, "axis": "x", "origin": [6.67, -2, 2.83]},
      "faces": {
        "north": {"uv": [8, 1.5, 11.875, 1.59375], "texture": "#0"},
        "east": {"uv": [7.5, 8.5, 8.4375, 8.59375], "texture": "#0"},
        "south": {"uv": [8, 2, 11.875, 2.09375], "texture": "#0"},
        "west": {"uv": [8.5, 8.5, 9.4375, 8.59375], "texture": "#0"},
        "up": {"uv": [3.875, 0.9375, 0, 0], "texture": "#0"},
        "down": {"uv": [3.875, 1, 0, 1.9375], "texture": "#0"}
      }
    },
    {
      "from": [5.745, 1.7, 9.49],
      "to": [13.515, 3.55, 9.675],
      "rotation": {"angle": 0, "axis": "y", "origin": [6.67, -2, 2.83]},
      "faces": {
        "north": {"uv": [0, 2, 3.875, 2.9375], "texture": "#0"},
        "east": {"uv": [0, 9, 0.09375, 9.9375], "texture": "#0"},
        "south": {"uv": [0, 3, 3.875, 3.9375], "texture": "#0"},
        "west": {"uv": [0.5, 9, 0.59375, 9.9375], "texture": "#0"},
        "up": {"uv": [11.875, 2.59375, 8, 2.5], "texture": "#0"},
        "down": {"uv": [6.875, 8, 3, 8.09375], "texture": "#0"}
      }
    },
    {
      "from": [5.745, 1.7, 5.235],
      "to": [13.515, 3.55, 5.42],
      "rotation": {"angle": 0, "axis": "y", "origin": [6.67, -2, 2.83]},
      "faces": {
        "north": {"uv": [0, 4, 3.875, 4.9375], "texture": "#0"},
        "east": {"uv": [1, 9, 1.09375, 9.9375], "texture": "#0"},
        "south": {"uv": [4, 0, 7.875, 0.9375], "texture": "#0"},
        "west": {"uv": [1.5, 9, 1.59375, 9.9375], "texture": "#0"},
        "up": {"uv": [11.875, 3.09375, 8, 3], "texture": "#0"},
        "down": {"uv": [11.875, 3.5, 8, 3.59375], "texture": "#0"}
      }
    },
    {
      "from": [5.745, -2.925, 11.34],
      "to": [13.515, -1.075, 11.525],
      "rotation": {"angle": -45, "axis": "x", "origin": [6.67, -2, 2.83]},
      "faces": {
        "north": {"uv": [4, 1, 7.875, 1.9375], "texture": "#0"},
        "east": {"uv": [2, 9, 2.09375, 9.9375], "texture": "#0"},
        "south": {"uv": [4, 2, 7.875, 2.9375], "texture": "#0"},
        "west": {"uv": [2.5, 9, 2.59375, 9.9375], "texture": "#0"},
        "up": {"uv": [11.875, 4.09375, 8, 4], "texture": "#0"},
        "down": {"uv": [11.875, 4.5, 8, 4.59375], "texture": "#0"}
      }
    },
    {
      "from": [5.745, -2.925, 7.085],
      "to": [13.515, -1.075, 7.27],
      "rotation": {"angle": -45, "axis": "x", "origin": [6.67, -2, 2.83]},
      "faces": {
        "north": {"uv": [4, 3, 7.875, 3.9375], "texture": "#0"},
        "east": {"uv": [3, 9, 3.09375, 9.9375], "texture": "#0"},
        "south": {"uv": [4, 4, 7.875, 4.9375], "texture": "#0"},
        "west": {"uv": [3.5, 9, 3.59375, 9.9375], "texture": "#0"},
        "up": {"uv": [11.875, 5.09375, 8, 5], "texture": "#0"},
        "down": {"uv": [11.875, 5.5, 8, 5.59375], "texture": "#0"}
      }
    },
    {
      "from": [5.745, 4.63, 6.53],
      "to": [13.515, 4.815, 8.38],
      "rotation": {"angle": 0, "axis": "y", "origin": [6.67, -2, 2.83]},
      "faces": {
        "north": {"uv": [8, 6, 11.875, 6.09375], "texture": "#0"},
        "east": {"uv": [4, 9, 4.9375, 9.09375], "texture": "#0"},
        "south": {"uv": [8, 6.5, 11.875, 6.59375], "texture": "#0"},
        "west": {"uv": [5, 9, 5.9375, 9.09375], "texture": "#0"},
        "up": {"uv": [3.875, 5.9375, 0, 5], "texture": "#0"},
        "down": {"uv": [7.875, 5, 4, 5.9375], "texture": "#0"}
      }
    },
    {
      "from": [5.745, 0.405, 6.53],
      "to": [13.515, 0.59, 8.38],
      "rotation": {"angle": 0, "axis": "y", "origin": [6.67, -2, 2.83]},
      "faces": {
        "north": {"uv": [7, 8, 10.875, 8.09375], "texture": "#0"},
        "east": {"uv": [6, 9, 6.9375, 9.09375], "texture": "#0"},
        "south": {"uv": [8, 7, 11.875, 7.09375], "texture": "#0"},
        "west": {"uv": [7, 9, 7.9375, 9.09375], "texture": "#0"},
        "up": {"uv": [3.875, 6.9375, 0, 6], "texture": "#0"},
        "down": {"uv": [7.875, 6, 4, 6.9375], "texture": "#0"}
      }
    },
    {
      "from": [5.745, 0.035, 8.38],
      "to": [13.515, 0.22, 10.23],
      "rotation": {"angle": -45, "axis": "x", "origin": [6.67, -2, 2.83]},
      "faces": {
        "north": {"uv": [8, 7.5, 11.875, 7.59375], "texture": "#0"},
        "east": {"uv": [8, 9, 8.9375, 9.09375], "texture": "#0"},
        "south": {"uv": [1.5, 8.5, 5.375, 8.59375], "texture": "#0"},
        "west": {"uv": [9, 9, 9.9375, 9.09375], "texture": "#0"},
        "up": {"uv": [3.875, 7.9375, 0, 7], "texture": "#0"},
        "down": {"uv": [7.875, 7, 4, 7.9375], "texture": "#0"}
      }
    },
    {
      "from": [7.965, 6.695, 2.09],
      "to": [10.185, 7.435, 3.57],
      "rotation": {"angle": 45, "axis": "x", "origin": [6.67, -2, 2.83]},
      "faces": {
        "north": {"uv": [8, 1, 9.125, 1.375], "texture": "#0"},
        "east": {"uv": [5.5, 8.5, 6.25, 8.875], "texture": "#0"},
        "south": {"uv": [1.5, 8, 2.625, 8.375], "texture": "#0"},
        "west": {"uv": [6.5, 8.5, 7.25, 8.875], "texture": "#0"},
        "up": {"uv": [1.125, 8.75, 0, 8], "texture": "#0"},
        "down": {"uv": [9.125, 0, 8, 0.75], "texture": "#0"}
      }
    }
  ],
  "display": {
    "thirdperson_righthand": {
      "rotation": [75, 45, 0],
      "translation": [0, 2, 3.25],
      "scale": [0.6, 0.6, 0.61]
    },
    "thirdperson_lefthand": {
      "rotation": [75, 45, 0],
      "translation": [0, 2, 3.25],
      "scale": [0.6, 0.6, 0.61]
    },
    "firstperson_righthand": {
      "rotation": [0, -90, 25],
      "translation": [-1.37, 5.95, 1.13],
      "scale": [0.68, 0.68, 0.68]
    },
    "firstperson_lefthand": {
      "rotation": [0, -90, 25],
      "translation": [-1.37, 5.95, 1.13],
      "scale": [0.68, 0.68, 0.68]
    },
    "ground": {
      "rotation": [64, -180, 0],
      "scale": [0.6, 0.6, 0.61]
    },
    "gui": {
      "rotation": [30, 225, 0],
      "translation": [1.25, 7.75, 0],
      "scale": [1.37, 1.37, 1.37]
    },
    "head": {
      "rotation": [64, -180, 0],
      "translation": [1, 9.5, 2.25],
      "scale": [0.6, 0.6, 0.61]
    },
    "fixed": {
      "translation": [-2, 5.75, 0]
    }
  },
  "groups": [
    {
      "name": "Big Log",
      "origin": [8, 8, 8],
      "color": 0,
      "children": [0, 1, 2, 3, 4, 5, 6, 7, 8]
    }
  ]
}